tcalls/__init__.py
tcalls/openai_tool_call.py
tcalls/py.typed
tcalls-0.0.1.dist-info/METADATA
tcalls-0.0.1.dist-info/WHEEL
tcalls-0.0.1.dist-info/RECORD
